LICENSE
MANIFEST.in
README.rst
qopenvpn.desktop
qopenvpn.png
setup.py
QOpenVPN.egg-info/PKG-INFO
QOpenVPN.egg-info/SOURCES.txt
QOpenVPN.egg-info/dependency_links.txt
QOpenVPN.egg-info/entry_points.txt
QOpenVPN.egg-info/top_level.txt
qopenvpn/__init__.py
qopenvpn/__main__.py
qopenvpn/openvpn.svg
qopenvpn/openvpn_disabled.svg
qopenvpn/qopenvpnlogviewer.ui
qopenvpn/qopenvpnsettings.ui
qopenvpn/stun.py
qopenvpn/ui_qopenvpnlogviewer.py
qopenvpn/ui_qopenvpnsettings.py
qopenvpn/version.py
qopenvpn/languages/qopenvpn_cs.qm
qopenvpn/languages/qopenvpn_cs.ts