Metadata-Version: 1.1
Name: QOpenVPN
Version: 1.3.3
Summary: Simple OpenVPN GUI written in PyQt for systemd based distributions
Home-page: https://github.com/xmikos/qopenvpn
Author: Michal Krenek (Mikos)
Author-email: m.krenek@gmail.com
License: GNU GPLv3
Platform: UNKNOWN
Classifier: Development Status :: 5 - Production/Stable
Classifier: Environment :: X11 Applications :: Qt
Classifier: Intended Audience :: End Users/Desktop
Classifier: Intended Audience :: System Administrators
Classifier: License :: OSI Approved :: GNU General Public License v3 or later (GPLv3+)
Classifier: Natural Language :: English
Classifier: Operating System :: POSIX :: Linux
Classifier: Programming Language :: Python :: 3
Classifier: Topic :: Security :: Cryptography
Classifier: Topic :: System :: Networking
